redis_sniffer/sniffer.py
redis_sniffer/main.py
redis_sniffer/log.py
redis_sniffer/__init__.py
redis_sniffer-1.1.0.dist-info/METADATA
redis_sniffer-1.1.0.dist-info/RECORD
redis_sniffer-1.1.0.dist-info/metadata.json
redis_sniffer-1.1.0.dist-info/WHEEL
redis_sniffer-1.1.0.dist-info/entry_points.txt
redis_sniffer-1.1.0.dist-info/DESCRIPTION.rst
redis_sniffer-1.1.0.dist-info/top_level.txt
