Metadata-Version: 2.0
Name: redis-sniffer
Version: 1.1.0
Summary: A redis sniffing & event logging utility
Home-page: https://github.com/eternalprojects/redis-sniffer
Author: Jesse Lesperance
Author-email: jesse@jplesperance.me
License: MIT
Keywords: Redis
Platform: UNKNOWN
Classifier: Topic :: Database
Classifier: Topic :: Utilities
Classifier: Topic :: System :: Systems Administration
Classifier: Programming Language :: Python
Requires-Dist: pypcap
Requires-Dist: dpkt
